vienna_smartmeter/__init__.py
vienna_smartmeter/_async/__init__.py
vienna_smartmeter/_async/client.py
vienna_smartmeter/client.py
vienna_smartmeter/errors.py
vienna_smartmeter-0.3.2.dist-info/LICENSE
vienna_smartmeter-0.3.2.dist-info/WHEEL
vienna_smartmeter-0.3.2.dist-info/METADATA
vienna_smartmeter-0.3.2.dist-info/RECORD
