Metadata-Version: 2.1
Name: vienna-smartmeter
Version: 0.3.2
Summary: Python library to access the Wiener Netze Smart Meter private API.
Home-page: https://github.com/platysma/vienna-smartmeter
License: MIT
Author: Platysma
Author-email: platysma.dev@gmail.com
Requires-Python: >=3.6.1,<4.0.0
Classifier: License :: OSI Approved :: MIT License
Classifier: Programming Language :: Python :: 3
Classifier: Programming Language :: Python :: 3.6
Classifier: Programming Language :: Python :: 3.7
Classifier: Programming Language :: Python :: 3.8
Classifier: Programming Language :: Python :: 3.9
Provides-Extra: async
Requires-Dist: aiohttp (>=3.7.4,<4.0.0); extra == "async"
Requires-Dist: async_timeout (>=3.0.1,<4.0.0); extra == "async"
Requires-Dist: importlib-metadata (>=4.6.4,<5.0.0)
Requires-Dist: lxml (>=4.6.3,<5.0.0)
Requires-Dist: requests (>=2.24.0,<3.0.0)
Project-URL: Changelog, https://github.com/platysma/vienna-smartmeter/releases
Project-URL: Repository, https://github.com/platysma/vienna-smartmeter
